LICENSE.txt
MANIFEST.in
README.rst
setup.py
giftwrap/__init__.py
giftwrap/auth.py
giftwrap/config.py
giftwrap/error.py
giftwrap/exchange.py
giftwrap/mock.py
giftwrap.egg-info/PKG-INFO
giftwrap.egg-info/SOURCES.txt
giftwrap.egg-info/dependency_links.txt
giftwrap.egg-info/requires.txt
giftwrap.egg-info/top_level.txt
giftwrap/exchanges/__init__.py
giftwrap/exchanges/_json.py
giftwrap/exchanges/_xml.py
giftwrap/test/__init__.py
giftwrap/test/test_exchange.py