Metadata-Version: 1.0
Name: giftwrap
Version: 1.5.7
Summary: Python Api Wrapping Toolset
Home-page: https://github.com/HubSpot/giftwrap
Author: prior
Author-email: mprior@hubspot.com
License: LICENSE.txt
Download-URL: https://github.com/HubSpot/giftwrap/tarball/v1.5.7
Platform: any
